vehicle_lib/__init__.py
vehicle_lib/vehicle.py
vehicle_lib-0.5.dist-info/METADATA
vehicle_lib-0.5.dist-info/WHEEL
vehicle_lib-0.5.dist-info/top_level.txt
vehicle_lib-0.5.dist-info/RECORD
