Metadata-Version: 2.1
Name: vehicle-lib
Version: 0.5
Summary: UNKNOWN
Home-page: UNKNOWN
License: UNKNOWN
Platform: UNKNOWN
Requires-Dist: opencv-python
Requires-Dist: torch
Requires-Dist: ultralytics
